setup.py
pgdb/__init__.py
pgdb/pgdb.py
pgdb.egg-info/PKG-INFO
pgdb.egg-info/SOURCES.txt
pgdb.egg-info/dependency_links.txt
pgdb.egg-info/requires.txt
pgdb.egg-info/top_level.txt
pgdb.egg-info/zip-safe