Metadata-Version: 1.1
Name: pgdb
Version: 0.0.5
Summary: PostgreSQL wrapper
Home-page: https://github.com/KehaoWu/pgdb
Author: @wukehao
Author-email: kehao.wu@gmail.com
License: Apache v2.0
Keywords: psql postgres postgresql sql wrapper
Platform: UNKNOWN
Classifier: Development Status :: 5 - Production/Stable
Classifier: License :: OSI Approved :: Apache Software License
Classifier: Programming Language :: Python :: 3.5
Classifier: Programming Language :: SQL
Classifier: Topic :: Database
